chembl_sqlalchemy.py
chembl_sqlalchemy-1.0.35.dist-info/METADATA
chembl_sqlalchemy-1.0.35.dist-info/WHEEL
chembl_sqlalchemy-1.0.35.dist-info/top_level.txt
chembl_sqlalchemy-1.0.35.dist-info/RECORD
