Metadata-Version: 2.4
Name: chembl-sqlalchemy
Version: 1.0.35
Summary: SQLAlchemy ORM schema for ChEMBL.
Author-email: Tim Hörmann <pypi@audivir.de>
License-Expression: MIT
Project-URL: Homepage, https://github.com/audivir/chembl-sqlalchemy
Project-URL: Documentation, https://github.com/audivir/chembl-sqlalchemy
Requires-Python: >=3.9
Requires-Dist: sqlalchemy>=2.0
Provides-Extra: dev
Requires-Dist: ruff; extra == "dev"
Requires-Dist: mypy; extra == "dev"
Requires-Dist: pytest; extra == "dev"
Requires-Dist: coverage[toml]; extra == "dev"
Requires-Dist: vulture; extra == "dev"
